com_pac/__about__.py
com_pac/__init__.py
com_pac/core.py
com_pac-0.0.3.dist-info/METADATA
com_pac-0.0.3.dist-info/WHEEL
com_pac-0.0.3.dist-info/entry_points.txt
com_pac-0.0.3.dist-info/licenses/LICENSE.txt
com_pac-0.0.3.dist-info/RECORD
